{"version":1,"generation_timestamp":"2020-05-17T16:04:01.141315Z","shops":[{"title":"White Herb","owner":"The Alchemist of Strahl","location":{"map":"prontera","x":123,"y":66},"creation_date":"2020-05-17T16:03:51Z","type":"B","items":[{"item_id":509,"amount":725,"price":620}]},{"title":"+7 Muffler [1] 5,5","owner":"Ryu??","location":{"map":"prontera","x":62,"y":214},"creation_date":"2020-05-17T16:03:50Z","type":"V","items":[{"item_id":2504,"amount":1,"price":5499999,"refine":7}]},{"title":"===_Shopi_===","owner":"Dilan","location":{"map":"prontera","x":104,"y":244},"creation_date":"2020-05-17T16:03:17Z","type":"V","items":[{"item_id":2626,"amount":1,"price":99000},{"item_id":2339,"amount":1,"price":4400},{"item_id":2339,"amount":1,"price":4400},{"item_id":2339,"amount":1,"price":4400},{"item_id":2402,"amount":1,"price":85000},{"item_id":2402,"amount":1,"price":85000},{"item_id":2402,"amount":1,"price":85000},{"item_id":2402,"amount":1,"price":85000}]},{"title":"ELUNIUM | ORIDECON","owner":"Buy Now","location":{"map":"payon","x":151,"y":166},"creation_date":"2020-05-17T16:02:03Z","type":"V","items":[{"item_id":985,"amount":72,"price":13000},{"item_id":984,"amount":103,"price":5000}]},{"title":"CHEAPEST Strawberry","owner":"Godzina","location":{"map":"prontera","x":93,"y":194},"creation_date":"2020-05-17T16:01:50Z","type":"V","items":[{"item_id":2502,"amount":1,"price":10000},{"item_id":2502,"amount":1,"price":10000},{"item_id":2502,"amount":1,"price":10000},{"item_id":2402,"amount":1,"price":85000},{"item_id":578,"amount":183,"price":998},{"item_id":10007,"amount":1,"price":10000},{"item_id":10007,"amount":1,"price":10000}]},{"title":"B\u003e r. Ori","owner":"jawel","location":{"map":"prontera","x":185,"y":216},"creation_date":"2020-05-17T16:01:24Z","type":"B","items":[{"item_id":756,"amount":250,"price":500},{"item_id":972,"amount":50,"price":8000}]},{"title":"NILE ROSE \u0026 MORE","owner":"Vencart","location":{"map":"prontera","x":188,"y":169},"creation_date":"2020-05-17T15:59:54Z","type":"V","items":[{"item_id":2319,"amount":1,"price":990000},{"item_id":2658,"amount":1,"price":700000},{"item_id":2658,"amount":1,"price":700000},{"item_id":2651,"amount":1,"price":600000},{"item_id":2650,"amount":1,"price":500000},{"item_id":603,"amount":4,"price":29000},{"item_id":4213,"amount":1,"price":300000}]},{"title":"White Herb","owner":"The Alchemist of Arland","location":{"map":"prontera","x":123,"y":68},"creation_date":"2020-05-17T15:59:52Z","type":"B","items":[{"item_id":509,"amount":725,"price":620}]},{"title":"\u003e bala's shop \u003c","owner":"bala","location":{"map":"prontera","x":229,"y":196},"creation_date":"2020-05-17T15:59:34Z","type":"V","items":[{"item_id":1223,"amount":1,"price":1475000},{"item_id":2308,"amount":1,"price":150000}]},{"title":"Strawberry","owner":"taxara","location":{"map":"prontera","x":181,"y":215},"creation_date":"2020-05-17T15:57:57Z","type":"V","items":[{"item_id":578,"amount":3998,"price":1200},{"item_id":4322,"amount":4,"price":500000}]},{"title":"STRAWBERRY","owner":"CROXat","location":{"map":"payon","x":177,"y":145},"creation_date":"2020-05-17T15:57:08Z","type":"B","items":[{"item_id":578,"amount":2500,"price":910}]},{"title":"FANCY FLOWER/CARD/BOW","owner":"Dressia","location":{"map":"prontera","x":147,"y":244},"creation_date":"2020-05-17T15:56:50Z","type":"V","items":[{"item_id":4037,"amount":1,"price":149000},{"item_id":2207,"amount":1,"price":129000},{"item_id":1708,"amount":1,"price":29999}]},{"title":"QUICK G FERUS SHOP","owner":"Polarn","location":{"map":"prontera","x":193,"y":218},"creation_date":"2020-05-17T15:54:45Z","type":"V","items":[{"item_id":4381,"amount":1,"price":10300000}]},{"title":"BIO2 Stuff","owner":"YogiYo","location":{"map":"prontera","x":204,"y":232},"creation_date":"2020-05-17T15:53:59Z","type":"V","items":[{"item_id":4347,"amount":4,"price":400000},{"item_id":4350,"amount":1,"price":400000},{"item_id":1223,"amount":1,"price":1500000},{"item_id":1223,"amount":1,"price":1500000},{"item_id":1523,"amount":1,"price":400000},{"item_id":1523,"amount":1,"price":400000}]},{"title":"Strawberry","owner":"ZenyZen","location":{"map":"payon","x":142,"y":47},"creation_date":"2020-05-17T15:53:50Z","type":"B","items":[{"item_id":578,"amount":2700,"price":900}]},{"title":"FLAME HEART","owner":"CROXat1","location":{"map":"prontera","x":164,"y":137},"creation_date":"2020-05-17T15:53:43Z","type":"B","items":[{"item_id":994,"amount":160,"price":3400},{"item_id":7296,"amount":20,"price":2000}]},{"title":"EbAy - STUFF \u0026 be Lazy like toder","owner":"Ebay01","location":{"map":"payon","x":139,"y":42},"creation_date":"2020-05-17T15:53:37Z","type":"V","items":[{"item_id":1602,"amount":1,"price":1500},{"item_id":1602,"amount":1,"price":1550},{"item_id":1602,"amount":1,"price":1600},{"item_id":1602,"amount":1,"price":1650},{"item_id":1602,"amount":1,"price":1700},{"item_id":1602,"amount":1,"price":1750},{"item_id":1602,"amount":1,"price":1800},{"item_id":1602,"amount":1,"price":1850},{"item_id":1602,"amount":1,"price":1900},{"item_id":1602,"amount":1,"price":1950},{"item_id":1602,"amount":1,"price":2000},{"item_id":1208,"amount":1,"price":19000}]},{"title":"White Herb","owner":"Knight\u003c3","location":{"map":"prontera","x":123,"y":70},"creation_date":"2020-05-17T15:53:17Z","type":"B","items":[{"item_id":509,"amount":825,"price":620}]},{"title":"STRAWBERRY","owner":"CROXsell","location":{"map":"prontera","x":164,"y":141},"creation_date":"2020-05-17T15:52:18Z","type":"V","items":[{"item_id":578,"amount":2461,"price":1000},{"item_id":994,"amount":99,"price":4850},{"item_id":10019,"amount":1,"price":10000},{"item_id":10019,"amount":1,"price":10000},{"item_id":751,"amount":1,"price":10000000}]},{"title":"White Herb","owner":"-KENSEI-","location":{"map":"prontera","x":123,"y":72},"creation_date":"2020-05-17T15:51:21Z","type":"B","items":[{"item_id":509,"amount":725,"price":620}]},{"title":"Post","owner":"Growe","location":{"map":"prontera","x":49,"y":219},"creation_date":"2020-05-17T15:48:37Z","type":"V","items":[{"item_id":1022,"amount":1779,"price":500},{"item_id":525,"amount":318,"price":500}]},{"title":"10 Top Pots Blue GEMS","owner":"EasyRares","location":{"map":"prontera","x":210,"y":197},"creation_date":"2020-05-17T15:48:32Z","type":"V","items":[{"item_id":715,"amount":1000,"price":1000},{"item_id":505,"amount":333,"price":4195,"creator":303593}]},{"title":"B\u003e Honey 600","owner":"Bio Weapon","location":{"map":"gonryun","x":152,"y":189},"creation_date":"2020-05-17T15:47:23Z","type":"B","items":[{"item_id":518,"amount":380,"price":600}]},{"title":"CLIP CLIP CLIP","owner":"MootMoot12","location":{"map":"prontera","x":95,"y":216},"creation_date":"2020-05-17T15:47:03Z","type":"V","items":[{"item_id":2607,"amount":1,"price":990000}]},{"title":"m","owner":"Merccyy","location":{"map":"prontera","x":118,"y":111},"creation_date":"2020-05-17T15:46:56Z","type":"V","items":[{"item_id":30016,"amount":1,"price":4500000},{"item_id":5141,"amount":1,"price":7200000,"refine":7},{"item_id":5121,"amount":1,"price":6200000,"creator":327891},{"item_id":4293,"amount":2,"price":250000}]},{"title":"SALE SALE SALE SALE","owner":"PAKETA","location":{"map":"prontera","x":119,"y":166},"creation_date":"2020-05-17T15:45:18Z","type":"V","items":[{"item_id":4031,"amount":2,"price":980000}]},{"title":"Items for U ^.^","owner":"Trasielia","location":{"map":"prontera","x":213,"y":193},"creation_date":"2020-05-17T15:43:49Z","type":"V","items":[{"item_id":1019,"amount":800,"price":3499},{"item_id":1024,"amount":49,"price":3499},{"item_id":7027,"amount":70,"price":29999},{"item_id":568,"amount":304,"price":498},{"item_id":5086,"amount":1,"price":4999999},{"item_id":5027,"amount":1,"price":2999999},{"item_id":5070,"amount":1,"price":1599999},{"item_id":5001,"amount":1,"price":899999},{"item_id":2292,"amount":1,"price":499999},{"item_id":2292,"amount":1,"price":499999},{"item_id":2281,"amount":1,"price":399999},{"item_id":2281,"amount":1,"price":399999}]},{"title":"B\u003e ELUS - 9K","owner":"MootMoot11","location":{"map":"prontera","x":200,"y":224},"creation_date":"2020-05-17T15:43:29Z","type":"B","items":[{"item_id":985,"amount":190,"price":9000}]},{"title":"CoronaTime™","owner":"Sell Buy","location":{"map":"prontera","x":116,"y":150},"creation_date":"2020-05-17T15:43:00Z","type":"V","items":[{"item_id":2607,"amount":1,"price":1050000},{"item_id":2607,"amount":1,"price":1050000},{"item_id":2607,"amount":1,"price":1050000},{"item_id":5124,"amount":1,"price":690000},{"item_id":5126,"amount":1,"price":740000},{"item_id":1264,"amount":1,"price":440000},{"item_id":2336,"amount":1,"price":640000},{"item_id":2406,"amount":1,"price":490000},{"item_id":1910,"amount":1,"price":800000},{"item_id":4281,"amount":6,"price":780000}]},{"title":"BananZa Shop™","owner":"Multibillionaire","location":{"map":"prontera","x":123,"y":160},"creation_date":"2020-05-17T15:42:49Z","type":"V","items":[{"item_id":2607,"amount":1,"price":1050000},{"item_id":2607,"amount":1,"price":1050000},{"item_id":2607,"amount":1,"price":1050000},{"item_id":5126,"amount":1,"price":740000},{"item_id":5126,"amount":1,"price":740000},{"item_id":5124,"amount":1,"price":690000},{"item_id":5124,"amount":1,"price":690000},{"item_id":2102,"amount":1,"price":250000},{"item_id":2336,"amount":1,"price":640000},{"item_id":1264,"amount":1,"price":440000}]},{"title":"STUFF CHEAPEST MARKET","owner":"Sellstuff","location":{"map":"geffen","x":130,"y":67},"creation_date":"2020-05-17T15:41:49Z","type":"V","items":[{"item_id":5057,"amount":1,"price":1199999},{"item_id":5057,"amount":1,"price":1199999},{"item_id":5057,"amount":1,"price":1199999},{"item_id":2506,"amount":1,"price":599999},{"item_id":5069,"amount":1,"price":999999,"refine":4},{"item_id":5671,"amount":1,"price":3999999},{"item_id":13405,"amount":1,"price":3000000,"refine":5,"cards":[4035,4035]}]},{"title":"asdsadsa","owner":"DarkMoney","location":{"map":"prontera","x":131,"y":88},"creation_date":"2020-05-17T15:40:54Z","type":"V","items":[{"item_id":4275,"amount":1,"price":1250000},{"item_id":4079,"amount":1,"price":1150000},{"item_id":2602,"amount":1,"price":1250000},{"item_id":2602,"amount":1,"price":1250000},{"item_id":1520,"amount":1,"price":175000},{"item_id":1264,"amount":1,"price":425000},{"item_id":2227,"amount":1,"price":45000},{"item_id":2227,"amount":1,"price":45000},{"item_id":1226,"amount":1,"price":65000},{"item_id":1226,"amount":1,"price":65000},{"item_id":2217,"amount":1,"price":45000}]},{"title":"Evil Doll | Sphinx | Holden | Marina","owner":"Siop 3","location":{"map":"payon","x":162,"y":223},"creation_date":"2020-05-17T15:40:36Z","type":"V","items":[{"item_id":5671,"amount